rlclient/__init__.py
rlclient/client.py
rlclient/methods.py
rlclient-0.2.1.dist-info/DESCRIPTION.rst
rlclient-0.2.1.dist-info/METADATA
rlclient-0.2.1.dist-info/RECORD
rlclient-0.2.1.dist-info/WHEEL
rlclient-0.2.1.dist-info/metadata.json
rlclient-0.2.1.dist-info/top_level.txt
