Metadata-Version: 2.0
Name: rlclient
Version: 0.2.1
Summary: UNKNOWN
Home-page: https://github.com/underyx/rlclient
Author: Bence Nagy
Author-email: bence@underyx.me
License: UNKNOWN
Download-URL: https://github.com/underyx/rlclient/releases
Platform: UNKNOWN
Classifier: Development Status :: 3 - Alpha
Classifier: Environment :: Console
Classifier: License :: OSI Approved :: MIT License
Classifier: Operating System :: OS Independent
Classifier: Programming Language :: Python :: 3.5
Requires-Dist: requests (>=2,<3)
